karabo_proxy/__init__.py
karabo_proxy/_version.py
karabo_proxy/async_karabo_proxy.py
karabo_proxy/message_format.py
karabo_proxy/sync_karabo_proxy.py
karabo_proxy/data/__init__.py
karabo_proxy/data/device_config.py
karabo_proxy/data/topology.py
karabo_proxy/data/web_proxy_responses.py
karabo_proxy/tests/__init__.py
karabo_proxy/tests/code_quality_test.py
karabo_proxy/tests/mock_web_proxy.py
karabo_proxy/tests/test_karabo_proxy.py
Karabo_proxy-1.0.4.dist-info/LICENSE
Karabo_proxy-1.0.4.dist-info/METADATA
Karabo_proxy-1.0.4.dist-info/WHEEL
Karabo_proxy-1.0.4.dist-info/top_level.txt
Karabo_proxy-1.0.4.dist-info/RECORD
