Metadata-Version: 2.1
Name: Karabo-proxy
Version: 1.0.4
Summary: Client library for the Karabo WebProxy with sync and async support
Author: costar & degon
License: BSD 3-Clause License
Project-URL: Homepage, https://github.com/European-XFEL/karabo_proxy
Requires-Python: >=3.8
License-File: LICENSE
Requires-Dist: aiodns
Requires-Dist: aiohttp >=3.9.0
Requires-Dist: requests >=2.28.0
Provides-Extra: test
Requires-Dist: flake8 ; extra == 'test'
Requires-Dist: isort >=5.10.0 ; extra == 'test'
Requires-Dist: pytest >=7.4.0 ; extra == 'test'
Requires-Dist: pytest-asyncio ; extra == 'test'
